mock_open/__init__.py
mock_open/mocks.py
mock_open/test/__init__.py
mock_open/test/test_mocks.py
mock_open/test/cpython/__init__.py
mock_open/test/cpython/testmock.py
mock_open/test/cpython/testwith.py
mock_open_hg-1.4.1.dist-info/LICENSE
mock_open_hg-1.4.1.dist-info/METADATA
mock_open_hg-1.4.1.dist-info/WHEEL
mock_open_hg-1.4.1.dist-info/top_level.txt
mock_open_hg-1.4.1.dist-info/RECORD
