Metadata-Version: 2.1
Name: mock-open-hg
Version: 1.4.1
Summary: A better mock for file I/O
Home-page: https://github.com/hairygeek/mock-open
Author: Niv Ben-David
Author-email: nivbend@gmail.com
License: MIT
Keywords: testing unittest test mock mocking patch patching stubs fakes doubles
Platform: UNKNOWN
Classifier: Development Status :: 5 - Production/Stable
Classifier: Environment :: Console
Classifier: Intended Audience :: Developers
Classifier: License :: OSI Approved :: MIT License
Classifier: Topic :: Software Development
Classifier: Topic :: Software Development :: Libraries
Classifier: Topic :: Software Development :: Libraries :: Python Modules
Classifier: Topic :: Software Development :: Testing
Classifier: Operating System :: OS Independent
Classifier: Programming Language :: Python
Classifier: Programming Language :: Python :: 2.7
Classifier: Programming Language :: Python :: 3
